[
  {
    "num": 1,
    "name": "创世记"
  },
  {
    "num": 2,
    "name": "出埃及记"
  },
  {
    "num": 3,
    "name": "利未记"
  },
  {
    "num": 4,
    "name": "民数记"
  },
  {
    "num": 5,
    "name": "申命记"
  },
  {
    "num": 6,
    "name": "约书亚记"
  },
  {
    "num": 7,
    "name": "士师记"
  },
  {
    "num": 8,
    "name": "路得记"
  },
  {
    "num": 9,
    "name": "撒母耳记上"
  },
  {
    "num": 10,
    "name": "撒母耳记下"
  },
  {
    "num": 11,
    "name": "列王纪上"
  },
  {
    "num": 12,
    "name": "列王纪下"
  },
  {
    "num": 13,
    "name": "历代志上"
  },
  {
    "num": 14,
    "name": "历代志下"
  },
  {
    "num": 15,
    "name": "以斯拉记"
  },
  {
    "num": 16,
    "name": "尼希米记"
  },
  {
    "num": 17,
    "name": "以斯帖记"
  },
  {
    "num": 18,
    "name": "约伯记"
  },
  {
    "num": 19,
    "name": "诗篇"
  },
  {
    "num": 20,
    "name": "箴言"
  },
  {
    "num": 21,
    "name": "传道书"
  },
  {
    "num": 22,
    "name": "雅歌"
  },
  {
    "num": 23,
    "name": "以赛亚书"
  },
  {
    "num": 24,
    "name": "耶利米书"
  },
  {
    "num": 25,
    "name": "耶利米哀歌"
  },
  {
    "num": 26,
    "name": "以西结书"
  },
  {
    "num": 27,
    "name": "但以理书"
  },
  {
    "num": 28,
    "name": "何西阿书"
  },
  {
    "num": 29,
    "name": "约珥书"
  },
  {
    "num": 30,
    "name": "阿摩司书"
  },
  {
    "num": 31,
    "name": "俄巴底亚书"
  },
  {
    "num": 32,
    "name": "约拿书"
  },
  {
    "num": 33,
    "name": "弥迦书"
  },
  {
    "num": 34,
    "name": "那鸿书"
  },
  {
    "num": 35,
    "name": "哈巴谷书"
  },
  {
    "num": 36,
    "name": "西番雅书"
  },
  {
    "num": 37,
    "name": "哈该书"
  },
  {
    "num": 38,
    "name": "撒迦利亚书"
  },
  {
    "num": 39,
    "name": "玛拉基书"
  },
  {
    "num": 40,
    "name": "马太福音"
  },
  {
    "num": 41,
    "name": "马可福音"
  },
  {
    "num": 42,
    "name": "路加福音"
  },
  {
    "num": 43,
    "name": "约翰福音"
  },
  {
    "num": 44,
    "name": "使徒行传"
  },
  {
    "num": 45,
    "name": "罗马书"
  },
  {
    "num": 46,
    "name": "哥林多前书"
  },
  {
    "num": 47,
    "name": "哥林多后书"
  },
  {
    "num": 48,
    "name": "加拉太书"
  },
  {
    "num": 49,
    "name": "以弗所书"
  },
  {
    "num": 50,
    "name": "腓立比书"
  },
  {
    "num": 51,
    "name": "歌罗西书"
  },
  {
    "num": 52,
    "name": "帖撒罗尼迦前书"
  },
  {
    "num": 53,
    "name": "帖撒罗尼迦后书"
  },
  {
    "num": 54,
    "name": "提摩太前书"
  },
  {
    "num": 55,
    "name": "提摩太后书"
  },
  {
    "num": 56,
    "name": "提多书"
  },
  {
    "num": 57,
    "name": "腓利门书"
  },
  {
    "num": 58,
    "name": "希伯来书"
  },
  {
    "num": 59,
    "name": "雅各书"
  },
  {
    "num": 60,
    "name": "彼得前书"
  },
  {
    "num": 61,
    "name": "彼得后书"
  },
  {
    "num": 62,
    "name": "约翰一书"
  },
  {
    "num": 63,
    "name": "约翰二书"
  },
  {
    "num": 64,
    "name": "约翰三书"
  },
  {
    "num": 65,
    "name": "犹大书"
  },
  {
    "num": 66,
    "name": "启示录"
  }
]